{
  "/care-services/page": "app/care-services/page.js",
  "/activity-management/page": "app/activity-management/page.js",
  "/visitor-management/page": "app/visitor-management/page.js",
  "/inventory-management/page": "app/inventory-management/page.js",
  "/nutrition-management/page": "app/nutrition-management/page.js",
  "/elderly-profiles/page": "app/elderly-profiles/page.js",
  "/health-monitoring/page": "app/health-monitoring/page.js",
  "/dashboard/page": "app/dashboard/page.js",
  "/alerts/page": "app/alerts/page.js",
  "/staff/page": "app/staff/page.js",
  "/login/page": "app/login/page.js",
  "/maintenance/page": "app/maintenance/page.js",
  "/document-management/page": "app/document-management/page.js"
}